<annotation>
	<folder>Images</folder>
	<filename>Invoice datasets_190709_0061.jpg</filename>
	<path>D:\Google Drive\Cinnamon AI\Data\NumberBox\Images\Invoice datasets_190709_0061.jpg</path>
	<source>
		<database>Unknown</database>
	</source>
	<size>
		<width>960</width>
		<height>1280</height>
		<depth>3</depth>
	</size>
	<segmented>0</segmented>
	<object>
		<name>Number_New</name>
		<pose>Unspecified</pose>
		<truncated>0</truncated>
		<difficult>0</difficult>
		<bndbox>
			<xmin>366</xmin>
			<ymin>533</ymin>
			<xmax>693</xmax>
			<ymax>612</ymax>
		</bndbox>
	</object>
	<object>
		<name>Date_New</name>
		<pose>Unspecified</pose>
		<truncated>0</truncated>
		<difficult>0</difficult>
		<bndbox>
			<xmin>224</xmin>
			<ymin>452</ymin>
			<xmax>718</xmax>
			<ymax>537</ymax>
		</bndbox>
	</object>
</annotation>
